mailer/__init__.py
mailer/admin.py
mailer/apps.py
mailer/models.py
mailer/providers.py
mailer/services.py
mailer/tests.py
mailer/utils.py
mailer/views.py
mailer/migrations/__init__.py
mailer/templates/admin/mailer_dashboard.html
pranky_mailer/__init__.py
pranky_mailer/asgi.py
pranky_mailer/settings.py
pranky_mailer/urls.py
pranky_mailer/wsgi.py
pranky_mailer-0.1.1.dist-info/METADATA
pranky_mailer-0.1.1.dist-info/WHEEL
pranky_mailer-0.1.1.dist-info/top_level.txt
pranky_mailer-0.1.1.dist-info/RECORD
