Metadata-Version: 2.4
Name: pranky-mailer
Version: 0.1.1
Summary: A Django app to send emails via multiple providers with logging and quota management
Home-page: https://github.com/prankycoders/pranky_mailer
Author: Ankit Bhardwaj
Author-email: ankitbhardwaj007@gmail.com
License: MIT
Classifier: Framework :: Django
Classifier: Programming Language :: Python :: 3
Classifier: License :: OSI Approved :: MIT License
Classifier: Operating System :: OS Independent
Requires-Dist: Django>=3.2
Requires-Dist: boto3>=1.26
Requires-Dist: requests>=2.28
Dynamic: author
Dynamic: author-email
Dynamic: classifier
Dynamic: description
Dynamic: description-content-type
Dynamic: home-page
Dynamic: license
Dynamic: requires-dist
Dynamic: summary
